homepress/__init__.py
homepress/__main__.py
homepress/bindermath.py
homepress/cli.py
homepress/layout/__init__.py
homepress/layout/pages.py
homepress/press.py
homepress/progress.py
homepress/renderer/__init__.py
homepress/renderer/multi_renderer.py
homepress/renderer/mupdf_renderer.py
homepress/renderer/page_range_renderer.py
homepress/renderer/pil_renderer.py
homepress/renderer/renderer_abc.py
homepress-2.1.0.dist-info/LICENSE.txt
homepress-2.1.0.dist-info/METADATA
homepress-2.1.0.dist-info/WHEEL
homepress-2.1.0.dist-info/entry_points.txt
homepress-2.1.0.dist-info/RECORD
