Metadata-Version: 2.1
Name: homepress
Version: 2.1.0
Summary: A swiss army knife of PDF printing and other documents. Can be used as a library.
Home-page: https://github.com/amaank404/homepress
License: MIT
Author: Amaan Ahmad Khan
Author-email: 71920621+amaank404@users.noreply.github.com
Requires-Python: >=3.12,<4.0
Classifier: License :: OSI Approved :: MIT License
Classifier: Programming Language :: Python :: 3
Classifier: Programming Language :: Python :: 3.12
Classifier: Programming Language :: Python :: 3.13
Requires-Dist: PyMuPDF (>=1.24.10,<2.0.0)
Requires-Dist: pillow (>=10.4.0,<11.0.0)
Project-URL: Repository, https://github.com/amaank404/homepress
